catl/__init__.py
catl/draft.py
catl/model.py
catl/predict.py
catl/text.py
catl/train.py
catl/utilities.py
catl/data/stopwords.txt
de_duplication/__init__.py
de_duplication/app.py
de_duplication/app1.py
de_duplication/minhash_duplication.py
de_duplication/process.py
de_duplication/simhash_duplication.py
download_data/__init__.py
download_data/download.py
julei/__init__.py
julei/app.py
julei/kmeans.py
julei/representation.py
julei/segment.py
julei/tfidf.py
julei/word2vec_train.py
julei/data/Tencent_AILab_ChineseEmbedding.txt
ner/__init__.py
ner/app.py
ner/extract.py
ner/feature_word.py
ner/data/feature_dict.txt
ner/data/province.txt
ner/data/合同信息抽取.xlsx
ner/data/国家名称.xlsx
ner/data/filter/address_filter.txt
ner/data/filter/capacity_filter.txt
ner/data/filter/entity_filter.txt
ner/data/filter/money_filter.txt
ner/data/filter/project_filter.txt
ner/data/filter/state_filter.txt
ner/data/filter/state_no_words.txt
ner/data/filter/time_filter.txt
ner/data/pattern/address_pattern.txt
ner/data/pattern/capacity_pattern.txt
ner/data/pattern/money_pattern.txt
ner/data/pattern/state_pattern.txt
ner/data/pattern/time_pattern.txt
relation_extraction/__init__.py
relation_extraction/app.py
relation_extraction/division.py
relation_extraction/hub_TextEmbedding.py
relation_extraction/id_input.py
relation_extraction/id_output.py
relation_extraction/preprocessing_xls.py
relation_extraction/rel_ext.py
relation_extraction/rel_prediction.py
relation_extraction/rel_train.py
relation_extraction/repeat.py
relation_extraction/test.py
relation_extraction/user_data/company.txt
relation_extraction/user_data/expert.txt
relation_extraction/user_data/leader.txt
relation_extraction/user_data/pre.xls
relation_extraction/user_data/predicted_result.xlsx
relation_extraction/user_data/region.txt
relation_extraction/user_data/researcharea.txt
relation_extraction/user_data/stop.txt
relation_extraction/user_data/userdict.txt
zzsnML-1.0.1.dist-info/DESCRIPTION.rst
zzsnML-1.0.1.dist-info/METADATA
zzsnML-1.0.1.dist-info/RECORD
zzsnML-1.0.1.dist-info/WHEEL
zzsnML-1.0.1.dist-info/metadata.json
zzsnML-1.0.1.dist-info/top_level.txt
