Metadata-Version: 2.0
Name: zzsnML
Version: 1.0.1
Summary: Python wrapper for zzsnML: natural language processing
Home-page: UNKNOWN
Author: chengtingting
Author-email: 2698641198@qq.com
License: UNKNOWN
Platform: UNKNOWN
